{
  "ID": "bvgd5qmg10l05lno1jd0",
  "Name": "index",
  "Attrs": {},
  "ParentID": "bvgd5qmg10l05lno1jc0",
  "Children": null,
  "Components": [
    {
      "ObjectID": "bvgd5qmg10l05lno1jd0",
      "ID": "bvgd5qmg10l05lno1jdg",
      "Name": "zt100.Page",
      "Enabled": true,
      "Attrs": null,
      "Value": {
        "HideInMenu": false,
        "OID": "bvgd5qmg10l05lno1jd0",
        "ObjectName": "index",
        "Title": "Home"
      },
      "Refs": null
    },
    {
      "ObjectID": "bvgd5qmg10l05lno1jd0",
      "ID": "bvgd64eg10l05lno1je0",
      "Name": "zt100.Block",
      "Enabled": true,
      "Attrs": null,
      "Value": {
        "BaseName": "image1",
        "ID": "bvgd64eg10l05lno1je0",
        "Image": null,
        "Name": "image1",
        "OID": "bvgd5qmg10l05lno1jd0",
        "Source": null,
        "Text": {}
      },
      "Refs": null
    }
  ],
  "Main": ""
}